__init__.py
parallel_marshall/__init__.py
parallel_marshall/balanced_distribution_iterator.py
parallel_marshall/parallel_marshall.py
scorep_jupyter/__init__.py
scorep_jupyter/install.py
scorep_jupyter/kernel.py
scorep_jupyter/kernel_messages.py
scorep_jupyter/logging_config.py
scorep_jupyter/logo.py
scorep_jupyter/userpersistence.py
scorep_jupyter-1.2.0.dist-info/licenses/LICENSE
scorep_jupyter-1.2.0.dist-info/METADATA
scorep_jupyter-1.2.0.dist-info/WHEEL
scorep_jupyter-1.2.0.dist-info/top_level.txt
scorep_jupyter-1.2.0.dist-info/RECORD
