Metadata-Version: 2.4
Name: scorep-jupyter
Version: 1.2.0
Summary: This is a Jupyter Python Kernel for Score-P instrumentation. It supports performance data recording with Score-P for fine-grained performance analysis.
Author-email: Elias Werner <elias.werner@tu-dresden.de>
License: Copyright (c) 2022, Technische Universitaet Dresden, Germany, all rights reserved.
Project-URL: homepage, https://github.com/score-p/scorep_jupyter_kernel_python
Project-URL: repository, https://github.com/score-p/scorep_jupyter_kernel_python
Classifier: Programming Language :: Python :: 3
Requires-Python: >=3.8
License-File: LICENSE
Requires-Dist: ipykernel
Requires-Dist: jupyter-client
Requires-Dist: astunparse
Requires-Dist: dill
Requires-Dist: scorep
Dynamic: license-file
